labequipment/__init__.py
labequipment/instruments/awg/signal_generator/SG384.py
labequipment/instruments/esa/E4440A.py
labequipment/instruments/esa/R3465.py
labequipment/instruments/lasers/AQ4321A.py
labequipment/instruments/lasers/TLB6700.py
labequipment/instruments/osa/AQ3675.py
labequipment/instruments/oscilloscopes/DS1104.py
labequipment/instruments/oscilloscopes/HP54810A.py
labequipment/instruments/oscilloscopes/TDS7404.py
labequipment/instruments/ssa/E5052A.py
labequipment/instruments/ssa/N9010A.py
labequipment-0.0.7.dist-info/METADATA
labequipment-0.0.7.dist-info/WHEEL
labequipment-0.0.7.dist-info/licenses/LICENSE
labequipment-0.0.7.dist-info/RECORD
