Metadata-Version: 2.3
Name: labequipment
Version: 0.0.7
Summary: A library for control of common lab equipment.
Project-URL: Homepage, https://github.com/tristanmelton/LabEquipment
Project-URL: Issues, https://github.com/tristanmelton/LabEquipment/issues
Author-email: Tristan Melton <tristanmelton@proton.me>
License-File: LICENSE
Classifier: License :: OSI Approved :: MIT License
Classifier: Operating System :: OS Independent
Classifier: Programming Language :: Python :: 3
Requires-Python: >=3.8
Requires-Dist: easy-scpi>=0.1.4
Requires-Dist: numpy>=1.26.0
Requires-Dist: pandas>=2.2.0
Requires-Dist: pythonnet>=3.0.3
Requires-Dist: pyvisa>=1.14.0
